LICENSE
MANIFEST.in
README.md
setup.py
cottonmouth/__init__.py
cottonmouth/constants.py
cottonmouth/html.py
cottonmouth/tags.py
cottonmouth.egg-info/PKG-INFO
cottonmouth.egg-info/SOURCES.txt
cottonmouth.egg-info/dependency_links.txt
cottonmouth.egg-info/top_level.txt