Metadata-Version: 1.0
Name: cottonmouth
Version: 0.1.3
Summary: Pure-Python HTML generation
Home-page: https://github.com/nosamanuel/cottonmouth
Author: Noah Seger
Author-email: nosamanuel@gmail.com.com
License: Copyright (c) 2013, Noah Seger
